secretflow_serving/tools/inferencer/inferencer
secretflow_serving_lib/__init__.py
secretflow_serving_lib/api.py
secretflow_serving_lib/attr_pb2.py
secretflow_serving_lib/bundle_pb2.py
secretflow_serving_lib/compute_trace_pb2.py
secretflow_serving_lib/config/__init__.py
secretflow_serving_lib/data_type_pb2.py
secretflow_serving_lib/feature_pb2.py
secretflow_serving_lib/graph_builder.py
secretflow_serving_lib/graph_pb2.py
secretflow_serving_lib/libserving.so
secretflow_serving_lib/link_function_pb2.py
secretflow_serving_lib/op_pb2.py
secretflow_serving_lib/secretflow_serving/config/cluster_config_pb2.py
secretflow_serving_lib/secretflow_serving/config/feature_config_pb2.py
secretflow_serving_lib/secretflow_serving/config/logging_config_pb2.py
secretflow_serving_lib/secretflow_serving/config/model_config_pb2.py
secretflow_serving_lib/secretflow_serving/config/retry_policy_config_pb2.py
secretflow_serving_lib/secretflow_serving/config/server_config_pb2.py
secretflow_serving_lib/secretflow_serving/config/serving_config_pb2.py
secretflow_serving_lib/secretflow_serving/config/tls_config_pb2.py
secretflow_serving_lib/secretflow_serving/config/trace_config_pb2.py
secretflow_serving_lib/secretflow_serving/protos/attr_pb2.py
secretflow_serving_lib/secretflow_serving/protos/bundle_pb2.py
secretflow_serving_lib/secretflow_serving/protos/compute_trace_pb2.py
secretflow_serving_lib/secretflow_serving/protos/data_type_pb2.py
secretflow_serving_lib/secretflow_serving/protos/feature_pb2.py
secretflow_serving_lib/secretflow_serving/protos/graph_pb2.py
secretflow_serving_lib/secretflow_serving/protos/link_function_pb2.py
secretflow_serving_lib/secretflow_serving/protos/op_pb2.py
secretflow_serving_lib/secretflow_serving/tools/inferencer/config_pb2.py
secretflow_serving_lib/version.py
secretflow_serving_lib-0.10.0.dev20250414.dist-info/WHEEL
secretflow_serving_lib-0.10.0.dev20250414.dist-info/METADATA
secretflow_serving_lib-0.10.0.dev20250414.dist-info/LICENSE
secretflow_serving_lib-0.10.0.dev20250414.dist-info/RECORD
