Metadata-Version: 2.1
Name: secretflow-serving-lib
Author: SecretFlow Team
Author-email: secretflow-contact@service.alipay.com
Home-page: https://github.com/secretflow/serving
License: Apache License 2.0
Summary: Serving is a subproject of Secretflow that implements model serving capabilities.
Classifier: Programming Language :: Python :: 3.9
Classifier: Programming Language :: Python :: 3.10
Classifier: Programming Language :: Python :: 3.11
Requires-Python: >=3.9
Requires-Dist: grpcio!=1.48.0,>=1.42.0
Requires-Dist: protobuf<5,>=4
Requires-Dist: pyarrow==14.0.2
Requires-Dist: numpy<2
Version: 0.10.0.dev20250414
